atls/__init__.py
atls/atls_context.py
atls/httpa_connection.py
atls/utils/__init__.py
atls/utils/_httpa_connection_shim.py
atls/utils/requests/__init__.py
atls/utils/requests/adapter.py
atls/utils/urllib3/__init__.py
atls/utils/urllib3/patch.py
atls/validators/__init__.py
atls/validators/validator.py
atls/validators/azure/__init__.py
atls/validators/azure/aas/__init__.py
atls/validators/azure/aas/aci_validator.py
atls/validators/azure/aas/cvm_validator.py
atls/validators/azure/aas/shared.py
pyatls-0.0.6.dist-info/LICENSE
pyatls-0.0.6.dist-info/METADATA
pyatls-0.0.6.dist-info/WHEEL
pyatls-0.0.6.dist-info/top_level.txt
pyatls-0.0.6.dist-info/RECORD
