Metadata-Version: 2.1
Name: pyatls
Version: 0.0.6
Summary: A Python package that implements Attested TLS (aTLS).
Author-email: Opaque Systems <pypi@opaque.co>
License: Apache License
Project-URL: Homepage, https://github.com/opaque-systems/atls-python
Keywords: atls,attestation,confidential,llm,privacy,security,ssl,tls
Classifier: Programming Language :: Python :: 3
Classifier: License :: OSI Approved :: Apache Software License
Requires-Python: >=3.8
License-File: LICENSE
Requires-Dist: cryptography
Requires-Dist: PyJWT
Requires-Dist: pyOpenSSL
Requires-Dist: urllib3 <2.1.0,>=2.0.0
Provides-Extra: requests
Requires-Dist: requests ; extra == 'requests'
